eds_tools/__init__.py
eds_tools/_version.py
eds_tools/eds_tools.py
eds_tools/sequence_utils.py
eds_tools/test_eds_tools.py
eds_tools-0.1.0.dist-info/LICENSE
eds_tools-0.1.0.dist-info/METADATA
eds_tools-0.1.0.dist-info/WHEEL
eds_tools-0.1.0.dist-info/top_level.txt
eds_tools-0.1.0.dist-info/RECORD
