Metadata-Version: 2.1
Name: eds-tools
Version: 0.1.0
Summary: EDSTools: designed to combined variant calls from peaked data with the reference genome. Returns the genomic sequence of the allele most present in the peak.
Author: Simone G. Riva, Edward Sanders
Author-email: simo.riva15@gmail.com
Project-URL: Bug Tracker, https://github.com/Genome-Function-Initiative-Oxford/EdTools/issues
Project-URL: Source, https://github.com/Genome-Function-Initiative-Oxford/EdTools
Requires-Python: >=3.9.10
License-File: LICENSE
Requires-Dist: pysam
